pybind11_vendor/_dummy.cpython-312-x86_64-linux-gnu.so
ros_pybind11_vendor-3.2.0.data/data/share/ament_index/resource_index/package_run_dependencies/pybind11_vendor
ros_pybind11_vendor-3.2.0.data/data/share/ament_index/resource_index/packages/pybind11_vendor
ros_pybind11_vendor-3.2.0.data/data/share/ament_index/resource_index/parent_prefix_path/pybind11_vendor
ros_pybind11_vendor-3.2.0.data/data/share/pybind11_vendor/local_setup.bash
ros_pybind11_vendor-3.2.0.data/data/share/pybind11_vendor/local_setup.dsv
ros_pybind11_vendor-3.2.0.data/data/share/pybind11_vendor/local_setup.sh
ros_pybind11_vendor-3.2.0.data/data/share/pybind11_vendor/local_setup.zsh
ros_pybind11_vendor-3.2.0.data/data/share/pybind11_vendor/package.dsv
ros_pybind11_vendor-3.2.0.data/data/share/pybind11_vendor/package.xml
ros_pybind11_vendor-3.2.0.data/data/share/pybind11_vendor/cmake/pybind11_vendor-extras.cmake
ros_pybind11_vendor-3.2.0.data/data/share/pybind11_vendor/cmake/pybind11_vendorConfig-version.cmake
ros_pybind11_vendor-3.2.0.data/data/share/pybind11_vendor/cmake/pybind11_vendorConfig.cmake
ros_pybind11_vendor-3.2.0.data/data/share/pybind11_vendor/environment/ament_prefix_path.dsv
ros_pybind11_vendor-3.2.0.data/data/share/pybind11_vendor/environment/ament_prefix_path.sh
ros_pybind11_vendor-3.2.0.data/data/share/pybind11_vendor/environment/path.dsv
ros_pybind11_vendor-3.2.0.data/data/share/pybind11_vendor/environment/path.sh
ros_pybind11_vendor-3.2.0.dist-info/METADATA
ros_pybind11_vendor-3.2.0.dist-info/WHEEL
ros_pybind11_vendor-3.2.0.dist-info/top_level.txt
ros_pybind11_vendor-3.2.0.dist-info/RECORD
ros_pybind11_vendor-3.2.0.dist-info/licenses/LICENSE
