Metadata-Version: 2.4
Name: ros-pybind11-vendor
Version: 3.2.0
Summary: Wheel for the pybind11_vendor (ros-pybind11-vendor) ROS 2 package.
License-File: LICENSE
Requires-Dist: pybind11
Dynamic: description
Dynamic: description-content-type
Dynamic: license-file
Dynamic: requires-dist
Dynamic: summary
